megalogger/__init__.py
megalogger/abstract_logger.py
megalogger/blueprints.py
megalogger/megalogged.py
megalogger/megalogging.py
megalogger-0.6.2.dist-info/METADATA
megalogger-0.6.2.dist-info/WHEEL
megalogger-0.6.2.dist-info/top_level.txt
megalogger-0.6.2.dist-info/RECORD
